courieruuid/__init__.py
courieruuid/generator.py
courieruuid-0.1.0.dist-info/LICENSE
courieruuid-0.1.0.dist-info/METADATA
courieruuid-0.1.0.dist-info/WHEEL
courieruuid-0.1.0.dist-info/top_level.txt
courieruuid-0.1.0.dist-info/RECORD
